{
  "config": {
    "network": "chunks_trace\\network.json",
    "movie": "chunks_trace\\movie.json",
    "abr": "bolae",
    "seek_config": "chunks_trace\\seeks_linear_hit_dynamic_miss.json",
    "seek_config_data": {
      "seeks": [
        {
          "seek_when": 39.5,
          "seek_to": 46.5
        },
        {
          "seek_when": 62.0,
          "seek_to": 69.1
        },
        {
          "seek_when": 84.6,
          "seek_to": 91.7
        },
        {
          "seek_when": 107.2,
          "seek_to": 114.2
        },
        {
          "seek_when": 129.7,
          "seek_to": 136.8
        },
        {
          "seek_when": 152.3,
          "seek_to": 159.3
        }
      ]
    },
    "prefetch_config": "chunks_trace\\prefetch_config.json",
    "network_multiplier": 1.0
  },
  "without_buffer_py": {
    "summary": {
      "played_utility": 87.400072,
      "played_bitrate": 99210.0,
      "total_play_time": 184.76,
      "total_rebuffer_time": 0.0,
      "rebuffer_ratio": 0.0,
      "rebuffer_count": 0,
      "qoe_score": 2.575971,
      "rampup_time": 4.26
    },
    "download_events": [
      {
        "start_time": 0,
        "end_time": 173,
        "segment": 0,
        "quality": 0,
        "buffer_level_before": 0,
        "buffer_level_after": 0
      },
      {
        "start_time": 173,
        "end_time": 2047,
        "segment": 1,
        "quality": 5,
        "buffer_level_before": 3765,
        "buffer_level_after": 3765
      },
      {
        "start_time": 2047,
        "end_time": 6403,
        "segment": 2,
        "quality": 5,
        "buffer_level_before": 5050,
        "buffer_level_after": 5050
      },
      {
        "start_time": 6403,
        "end_time": 10012,
        "segment": 3,
        "quality": 5,
        "buffer_level_before": 7081,
        "buffer_level_after": 7081
      },
      {
        "start_time": 10012,
        "end_time": 15796,
        "segment": 4,
        "quality": 5,
        "buffer_level_before": 6936,
        "buffer_level_after": 6936
      },
      {
        "start_time": 15796,
        "end_time": 23329,
        "segment": 5,
        "quality": 5,
        "buffer_level_before": 5043,
        "buffer_level_after": 5043
      },
      {
        "start_time": 23329,
        "end_time": 24687,
        "segment": 6,
        "quality": 4,
        "buffer_level_before": 9326,
        "buffer_level_after": 9326
      },
      {
        "start_time": 24687,
        "end_time": 26990,
        "segment": 7,
        "quality": 5,
        "buffer_level_before": 12663,
        "buffer_level_after": 12663
      },
      {
        "start_time": 26990,
        "end_time": 31013,
        "segment": 8,
        "quality": 5,
        "buffer_level_before": 14280,
        "buffer_level_after": 14280
      },
      {
        "start_time": 31573,
        "end_time": 35165,
        "segment": 9,
        "quality": 5,
        "buffer_level_before": 15768,
        "buffer_level_after": 15768
      },
      {
        "start_time": 39589,
        "end_time": 41816,
        "segment": 10,
        "quality": 4,
        "buffer_level_before": 7583,
        "buffer_level_after": 7583
      },
      {
        "start_time": 41906,
        "end_time": 44521,
        "segment": 11,
        "quality": 4,
        "buffer_level_before": 10519,
        "buffer_level_after": 10519
      },
      {
        "start_time": 44521,
        "end_time": 46313,
        "segment": 12,
        "quality": 4,
        "buffer_level_before": 14367,
        "buffer_level_after": 14367
      },
      {
        "start_time": 46960,
        "end_time": 50027,
        "segment": 13,
        "quality": 5,
        "buffer_level_before": 16292,
        "buffer_level_after": 16292
      },
      {
        "start_time": 52600,
        "end_time": 57763,
        "segment": 14,
        "quality": 5,
        "buffer_level_before": 14197,
        "buffer_level_after": 14197
      },
      {
        "start_time": 62082,
        "end_time": 63189,
        "segment": 15,
        "quality": 4,
        "buffer_level_before": 14311,
        "buffer_level_after": 14311
      },
      {
        "start_time": 63780,
        "end_time": 66168,
        "segment": 16,
        "quality": 5,
        "buffer_level_before": 16972,
        "buffer_level_after": 16972
      },
      {
        "start_time": 69420,
        "end_time": 77688,
        "segment": 17,
        "quality": 5,
        "buffer_level_before": 11092,
        "buffer_level_after": 11092
      },
      {
        "start_time": 77688,
        "end_time": 78294,
        "segment": 18,
        "quality": 4,
        "buffer_level_before": 16125,
        "buffer_level_after": 16125
      },
      {
        "start_time": 84600,
        "end_time": 86578,
        "segment": 19,
        "quality": 4,
        "buffer_level_before": 13481,
        "buffer_level_after": 13481
      },
      {
        "start_time": 86578,
        "end_time": 88162,
        "segment": 20,
        "quality": 5,
        "buffer_level_before": 17537,
        "buffer_level_after": 17537
      },
      {
        "start_time": 91980,
        "end_time": 97818,
        "segment": 21,
        "quality": 5,
        "buffer_level_before": 13521,
        "buffer_level_after": 13521
      },
      {
        "start_time": 97818,
        "end_time": 99450,
        "segment": 22,
        "quality": 5,
        "buffer_level_before": 17530,
        "buffer_level_after": 17530
      },
      {
        "start_time": 107200,
        "end_time": 108420,
        "segment": 23,
        "quality": 4,
        "buffer_level_before": 14300,
        "buffer_level_after": 14300
      },
      {
        "start_time": 113635,
        "end_time": 115236,
        "segment": 24,
        "quality": 3,
        "buffer_level_before": 13123,
        "buffer_level_after": 13123
      },
      {
        "start_time": 115236,
        "end_time": 115829,
        "segment": 25,
        "quality": 4,
        "buffer_level_before": 18171,
        "buffer_level_after": 18171
      },
      {
        "start_time": 120280,
        "end_time": 126486,
        "segment": 26,
        "quality": 5,
        "buffer_level_before": 13153,
        "buffer_level_after": 13153
      },
      {
        "start_time": 126486,
        "end_time": 128495,
        "segment": 27,
        "quality": 5,
        "buffer_level_before": 16785,
        "buffer_level_after": 16785
      },
      {
        "start_time": 131460,
        "end_time": 132548,
        "segment": 28,
        "quality": 4,
        "buffer_level_before": 18271,
        "buffer_level_after": 18271
      },
      {
        "start_time": 137100,
        "end_time": 140677,
        "segment": 29,
        "quality": 5,
        "buffer_level_before": 15783,
        "buffer_level_after": 15783
      },
      {
        "start_time": 142740,
        "end_time": 145005,
        "segment": 30,
        "quality": 5,
        "buffer_level_before": 17094,
        "buffer_level_after": 17094
      },
      {
        "start_time": 148380,
        "end_time": 151671,
        "segment": 31,
        "quality": 5,
        "buffer_level_before": 16069,
        "buffer_level_after": 16069
      },
      {
        "start_time": 154235,
        "end_time": 156329,
        "segment": 32,
        "quality": 4,
        "buffer_level_before": 17151,
        "buffer_level_after": 17151
      },
      {
        "start_time": 159760,
        "end_time": 160393,
        "segment": 33,
        "quality": 5,
        "buffer_level_before": 18726,
        "buffer_level_after": 18726
      }
    ],
    "prefetch_events": [],
    "seek_events": [
      {
        "seek_when_s": 39.5,
        "from_segment": 6,
        "seek_to_s": 46,
        "segment": 8
      },
      {
        "seek_when_s": 62.0,
        "from_segment": 12,
        "seek_to_s": 69,
        "segment": 12
      },
      {
        "seek_when_s": 84.6,
        "from_segment": 16,
        "seek_to_s": 91,
        "segment": 16
      },
      {
        "seek_when_s": 107.2,
        "from_segment": 20,
        "seek_to_s": 114,
        "segment": 20
      },
      {
        "seek_when_s": 129.699,
        "from_segment": 24,
        "seek_to_s": 136,
        "segment": 24
      },
      {
        "seek_when_s": 152.3,
        "from_segment": 28,
        "seek_to_s": 159,
        "segment": 28
      }
    ],
    "rebuffer_starts_s": [],
    "rebuffer_durations_s": [],
    "time_series": {
      "time_points": [
        0.173,
        2.047,
        6.403,
        10.012,
        15.796,
        20.839,
        23.329,
        24.687,
        26.99,
        31.013,
        35.165,
        41.816,
        44.521,
        46.313,
        50.027,
        57.763,
        63.189,
        66.168,
        77.688,
        78.294,
        86.578,
        88.162,
        97.818,
        99.45,
        108.42,
        115.236,
        115.829,
        126.486,
        128.495,
        132.548,
        140.677,
        145.005,
        151.671,
        156.329,
        160.393
      ],
      "buffer_levels": [
        0.0,
        3.765,
        5.05,
        7.081,
        6.936,
        0.0,
        5.043,
        9.326,
        12.663,
        14.28,
        15.768,
        7.583,
        10.519,
        14.367,
        16.292,
        14.197,
        14.311,
        16.972,
        11.092,
        16.125,
        13.481,
        17.537,
        13.521,
        17.53,
        14.3,
        13.123,
        18.171,
        13.153,
        16.785,
        18.271,
        15.783,
        17.094,
        16.069,
        17.151,
        18.726
      ],
      "qualities": [
        0,
        5,
        5,
        5,
        5,
        5,
        5,
        4,
        5,
        5,
        5,
        4,
        4,
        4,
        5,
        5,
        4,
        5,
        5,
        4,
        4,
        5,
        5,
        5,
        4,
        3,
        4,
        5,
        5,
        4,
        5,
        5,
        5,
        4,
        5
      ],
      "segments": [
        0,
        1,
        2,
        3,
        4,
        5,
        5,
        6,
        7,
        8,
        9,
        10,
        11,
        12,
        13,
        14,
        15,
        16,
        17,
        18,
        19,
        20,
        21,
        22,
        23,
        24,
        25,
        26,
        27,
        28,
        29,
        30,
        31,
        32,
        33
      ]
    }
  },
  "with_buffer_py": {
    "summary": {
      "played_utility": 85.193597,
      "played_bitrate": 93418.0,
      "total_play_time": 184.76,
      "total_rebuffer_time": 0.0,
      "rebuffer_ratio": 0.0,
      "rebuffer_count": 0,
      "qoe_score": 2.492379,
      "rampup_time": 4.26
    },
    "download_events": [
      {
        "start_time": 0,
        "end_time": 173,
        "segment": 0,
        "quality": 0,
        "buffer_level_before": 0,
        "buffer_level_after": 0
      },
      {
        "start_time": 173,
        "end_time": 2047,
        "segment": 1,
        "quality": 5,
        "buffer_level_before": 3765,
        "buffer_level_after": 3765
      },
      {
        "start_time": 2047,
        "end_time": 6403,
        "segment": 2,
        "quality": 5,
        "buffer_level_before": 5050,
        "buffer_level_after": 5050
      },
      {
        "start_time": 6403,
        "end_time": 10012,
        "segment": 3,
        "quality": 5,
        "buffer_level_before": 7081,
        "buffer_level_after": 7081
      },
      {
        "start_time": 10012,
        "end_time": 15796,
        "segment": 4,
        "quality": 5,
        "buffer_level_before": 6936,
        "buffer_level_after": 6936
      },
      {
        "start_time": 15796,
        "end_time": 23329,
        "segment": 5,
        "quality": 5,
        "buffer_level_before": 5043,
        "buffer_level_after": 5043
      },
      {
        "start_time": 23329,
        "end_time": 24687,
        "segment": 6,
        "quality": 4,
        "buffer_level_before": 9326,
        "buffer_level_after": 9326
      },
      {
        "start_time": 24687,
        "end_time": 26990,
        "segment": 7,
        "quality": 5,
        "buffer_level_before": 12663,
        "buffer_level_after": 12663
      },
      {
        "start_time": 38127,
        "end_time": 39178,
        "segment": 8,
        "quality": 4,
        "buffer_level_before": 11755,
        "buffer_level_after": 11755
      },
      {
        "start_time": 39500,
        "end_time": 41727,
        "segment": 10,
        "quality": 4,
        "buffer_level_before": 7672,
        "buffer_level_after": 7672
      },
      {
        "start_time": 46856,
        "end_time": 47689,
        "segment": 12,
        "quality": 3,
        "buffer_level_before": 12990,
        "buffer_level_after": 12990
      },
      {
        "start_time": 48284,
        "end_time": 49059,
        "segment": 13,
        "quality": 4,
        "buffer_level_before": 17260,
        "buffer_level_after": 17260
      },
      {
        "start_time": 52600,
        "end_time": 59274,
        "segment": 14,
        "quality": 5,
        "buffer_level_before": 12686,
        "buffer_level_after": 12686
      },
      {
        "start_time": 63780,
        "end_time": 65236,
        "segment": 16,
        "quality": 4,
        "buffer_level_before": 17904,
        "buffer_level_after": 17904
      },
      {
        "start_time": 69420,
        "end_time": 76884,
        "segment": 17,
        "quality": 5,
        "buffer_level_before": 11896,
        "buffer_level_after": 11896
      },
      {
        "start_time": 80700,
        "end_time": 84138,
        "segment": 19,
        "quality": 5,
        "buffer_level_before": 15921,
        "buffer_level_after": 15921
      },
      {
        "start_time": 86340,
        "end_time": 87283,
        "segment": 20,
        "quality": 4,
        "buffer_level_before": 18417,
        "buffer_level_after": 18417
      },
      {
        "start_time": 91980,
        "end_time": 95104,
        "segment": 21,
        "quality": 5,
        "buffer_level_before": 16235,
        "buffer_level_after": 16235
      },
      {
        "start_time": 103260,
        "end_time": 105565,
        "segment": 23,
        "quality": 5,
        "buffer_level_before": 17055,
        "buffer_level_after": 17055
      },
      {
        "start_time": 109100,
        "end_time": 112259,
        "segment": 24,
        "quality": 4,
        "buffer_level_before": 16100,
        "buffer_level_after": 16100
      },
      {
        "start_time": 114640,
        "end_time": 115477,
        "segment": 25,
        "quality": 4,
        "buffer_level_before": 18523,
        "buffer_level_after": 18523
      },
      {
        "start_time": 125920,
        "end_time": 128326,
        "segment": 27,
        "quality": 5,
        "buffer_level_before": 16953,
        "buffer_level_after": 16953
      },
      {
        "start_time": 131460,
        "end_time": 133433,
        "segment": 28,
        "quality": 4,
        "buffer_level_before": 17386,
        "buffer_level_after": 17386
      },
      {
        "start_time": 137100,
        "end_time": 139870,
        "segment": 29,
        "quality": 5,
        "buffer_level_before": 16589,
        "buffer_level_after": 16589
      },
      {
        "start_time": 148380,
        "end_time": 151487,
        "segment": 31,
        "quality": 5,
        "buffer_level_before": 16253,
        "buffer_level_after": 16253
      },
      {
        "start_time": 154196,
        "end_time": 155006,
        "segment": 32,
        "quality": 4,
        "buffer_level_before": 18473,
        "buffer_level_after": 18473
      },
      {
        "start_time": 159760,
        "end_time": 160874,
        "segment": 33,
        "quality": 5,
        "buffer_level_before": 18245,
        "buffer_level_after": 18245
      }
    ],
    "prefetch_events": [
      {
        "start_time": 26990,
        "end_time": 29213,
        "segment": 7,
        "quality": 5,
        "buffer_level_before": 18303,
        "buffer_level_after": 21719
      },
      {
        "start_time": 29213,
        "end_time": 34946,
        "segment": 11,
        "quality": 5,
        "buffer_level_before": 21719,
        "buffer_level_after": 15987
      },
      {
        "start_time": 34946,
        "end_time": 38127,
        "segment": 15,
        "quality": 5,
        "buffer_level_before": 15987,
        "buffer_level_after": 12806
      },
      {
        "start_time": 41727,
        "end_time": 44459,
        "segment": 18,
        "quality": 5,
        "buffer_level_before": 18952,
        "buffer_level_after": 16221
      },
      {
        "start_time": 44459,
        "end_time": 45177,
        "segment": 22,
        "quality": 4,
        "buffer_level_before": 16221,
        "buffer_level_after": 15503
      },
      {
        "start_time": 45177,
        "end_time": 46856,
        "segment": 26,
        "quality": 4,
        "buffer_level_before": 15503,
        "buffer_level_after": 13823
      },
      {
        "start_time": 47689,
        "end_time": 48284,
        "segment": 30,
        "quality": 4,
        "buffer_level_before": 18630,
        "buffer_level_after": 18035
      }
    ],
    "seek_events": [
      {
        "seek_when_s": 39.5,
        "from_segment": 6,
        "seek_to_s": 46,
        "segment": 8
      },
      {
        "seek_when_s": 62.0,
        "from_segment": 12,
        "seek_to_s": 69,
        "segment": 12
      },
      {
        "seek_when_s": 84.6,
        "from_segment": 16,
        "seek_to_s": 91,
        "segment": 16
      },
      {
        "seek_when_s": 107.2,
        "from_segment": 20,
        "seek_to_s": 114,
        "segment": 20
      },
      {
        "seek_when_s": 129.699,
        "from_segment": 24,
        "seek_to_s": 136,
        "segment": 24
      },
      {
        "seek_when_s": 152.3,
        "from_segment": 28,
        "seek_to_s": 159,
        "segment": 28
      }
    ],
    "rebuffer_starts_s": [],
    "rebuffer_durations_s": [],
    "time_series": {
      "time_points": [
        0.173,
        2.047,
        6.403,
        10.012,
        15.796,
        20.839,
        23.329,
        24.687,
        26.99,
        39.178,
        41.727,
        47.689,
        49.059,
        59.274,
        65.236,
        76.884,
        84.138,
        87.283,
        95.104,
        105.565,
        112.259,
        115.477,
        128.326,
        133.433,
        139.87,
        151.487,
        155.006,
        160.874
      ],
      "buffer_levels": [
        0.0,
        3.765,
        5.05,
        7.081,
        6.936,
        0.0,
        5.043,
        9.326,
        12.663,
        11.755,
        7.672,
        12.99,
        17.26,
        12.686,
        17.904,
        11.896,
        15.921,
        18.417,
        16.235,
        17.055,
        16.1,
        18.523,
        16.953,
        17.386,
        16.589,
        16.253,
        18.473,
        18.245
      ],
      "qualities": [
        0,
        5,
        5,
        5,
        5,
        5,
        5,
        4,
        5,
        4,
        4,
        3,
        4,
        5,
        4,
        5,
        5,
        4,
        5,
        5,
        4,
        4,
        5,
        4,
        5,
        5,
        4,
        5
      ],
      "segments": [
        0,
        1,
        2,
        3,
        4,
        5,
        5,
        6,
        7,
        8,
        10,
        12,
        13,
        14,
        16,
        17,
        19,
        20,
        21,
        23,
        24,
        25,
        27,
        28,
        29,
        31,
        32,
        33
      ]
    }
  }
}