{
  "config": {
    "network": "network.json",
    "movie": "movie.json",
    "abr": "bolae",
    "seek_config": "seeks.json",
    "prefetch_config": "test_prefetch_config.json",
    "network_multiplier": 1.0
  },
  "without_buffer_py": {
    "summary": {
      "played_utility": 300.026425,
      "played_bitrate": 280139.0,
      "total_play_time": 685.189212,
      "total_rebuffer_time": 176.795597,
      "rebuffer_ratio": 0.258024,
      "rebuffer_count": 17,
      "rampup_time": 3.2452
    },
    "download_events": [
      {
        "start_time": 0,
        "end_time": 804,
        "segment": 0,
        "quality": 0,
        "buffer_level_before": 0,
        "buffer_level_after": 0
      },
      {
        "start_time": 804,
        "end_time": 3102,
        "segment": 1,
        "quality": 4,
        "buffer_level_before": 702,
        "buffer_level_after": 702
      },
      {
        "start_time": 3102,
        "end_time": 4987,
        "segment": 2,
        "quality": 4,
        "buffer_level_before": 1817,
        "buffer_level_after": 1817
      },
      {
        "start_time": 4987,
        "end_time": 8088,
        "segment": 3,
        "quality": 4,
        "buffer_level_before": 1716,
        "buffer_level_after": 1716
      },
      {
        "start_time": 8088,
        "end_time": 10269,
        "segment": 4,
        "quality": 4,
        "buffer_level_before": 2535,
        "buffer_level_after": 2535
      },
      {
        "start_time": 10269,
        "end_time": 13282,
        "segment": 5,
        "quality": 5,
        "buffer_level_before": 2521,
        "buffer_level_after": 2521
      },
      {
        "start_time": 13282,
        "end_time": 16026,
        "segment": 6,
        "quality": 4,
        "buffer_level_before": 2777,
        "buffer_level_after": 2777
      },
      {
        "start_time": 16026,
        "end_time": 19243,
        "segment": 7,
        "quality": 4,
        "buffer_level_before": 2560,
        "buffer_level_after": 2560
      },
      {
        "start_time": 19243,
        "end_time": 21257,
        "segment": 8,
        "quality": 4,
        "buffer_level_before": 3547,
        "buffer_level_after": 3547
      },
      {
        "start_time": 21257,
        "end_time": 23661,
        "segment": 9,
        "quality": 4,
        "buffer_level_before": 4142,
        "buffer_level_after": 4142
      },
      {
        "start_time": 23661,
        "end_time": 26281,
        "segment": 10,
        "quality": 4,
        "buffer_level_before": 4523,
        "buffer_level_after": 4523
      },
      {
        "start_time": 26281,
        "end_time": 28740,
        "segment": 11,
        "quality": 4,
        "buffer_level_before": 5064,
        "buffer_level_after": 5064
      },
      {
        "start_time": 28740,
        "end_time": 30748,
        "segment": 12,
        "quality": 5,
        "buffer_level_before": 6056,
        "buffer_level_after": 6056
      },
      {
        "start_time": 30748,
        "end_time": 32161,
        "segment": 13,
        "quality": 5,
        "buffer_level_before": 7643,
        "buffer_level_after": 7643
      },
      {
        "start_time": 32161,
        "end_time": 34045,
        "segment": 14,
        "quality": 6,
        "buffer_level_before": 8758,
        "buffer_level_after": 8758
      },
      {
        "start_time": 34045,
        "end_time": 35764,
        "segment": 15,
        "quality": 6,
        "buffer_level_before": 10040,
        "buffer_level_after": 10040
      },
      {
        "start_time": 35764,
        "end_time": 38019,
        "segment": 16,
        "quality": 7,
        "buffer_level_before": 10785,
        "buffer_level_after": 10785
      },
      {
        "start_time": 38019,
        "end_time": 40962,
        "segment": 17,
        "quality": 7,
        "buffer_level_before": 10842,
        "buffer_level_after": 10842
      },
      {
        "start_time": 40962,
        "end_time": 43151,
        "segment": 18,
        "quality": 7,
        "buffer_level_before": 11653,
        "buffer_level_after": 11653
      },
      {
        "start_time": 43151,
        "end_time": 46285,
        "segment": 19,
        "quality": 7,
        "buffer_level_before": 11519,
        "buffer_level_after": 11519
      },
      {
        "start_time": 46285,
        "end_time": 48887,
        "segment": 20,
        "quality": 7,
        "buffer_level_before": 11917,
        "buffer_level_after": 11917
      },
      {
        "start_time": 48887,
        "end_time": 53261,
        "segment": 21,
        "quality": 8,
        "buffer_level_before": 10543,
        "buffer_level_after": 10543
      },
      {
        "start_time": 53261,
        "end_time": 55514,
        "segment": 22,
        "quality": 7,
        "buffer_level_before": 11290,
        "buffer_level_after": 11290
      },
      {
        "start_time": 55514,
        "end_time": 58454,
        "segment": 23,
        "quality": 7,
        "buffer_level_before": 11349,
        "buffer_level_after": 11349
      },
      {
        "start_time": 90004,
        "end_time": 90394,
        "segment": 24,
        "quality": 1,
        "buffer_level_before": 0,
        "buffer_level_after": 0
      },
      {
        "start_time": 90394,
        "end_time": 90907,
        "segment": 25,
        "quality": 2,
        "buffer_level_before": 2487,
        "buffer_level_after": 2487
      },
      {
        "start_time": 90907,
        "end_time": 91586,
        "segment": 26,
        "quality": 3,
        "buffer_level_before": 4808,
        "buffer_level_after": 4808
      },
      {
        "start_time": 91586,
        "end_time": 92607,
        "segment": 27,
        "quality": 4,
        "buffer_level_before": 6786,
        "buffer_level_after": 6786
      },
      {
        "start_time": 92607,
        "end_time": 93921,
        "segment": 28,
        "quality": 5,
        "buffer_level_before": 8472,
        "buffer_level_after": 8472
      },
      {
        "start_time": 93921,
        "end_time": 96210,
        "segment": 29,
        "quality": 6,
        "buffer_level_before": 9183,
        "buffer_level_after": 9183
      },
      {
        "start_time": 96210,
        "end_time": 98024,
        "segment": 30,
        "quality": 6,
        "buffer_level_before": 10370,
        "buffer_level_after": 10370
      },
      {
        "start_time": 98024,
        "end_time": 99994,
        "segment": 31,
        "quality": 6,
        "buffer_level_before": 11400,
        "buffer_level_after": 11400
      },
      {
        "start_time": 99994,
        "end_time": 102561,
        "segment": 32,
        "quality": 7,
        "buffer_level_before": 11833,
        "buffer_level_after": 11833
      },
      {
        "start_time": 102561,
        "end_time": 106074,
        "segment": 33,
        "quality": 7,
        "buffer_level_before": 11320,
        "buffer_level_after": 11320
      },
      {
        "start_time": 106074,
        "end_time": 108134,
        "segment": 34,
        "quality": 7,
        "buffer_level_before": 12260,
        "buffer_level_after": 12260
      },
      {
        "start_time": 108134,
        "end_time": 111372,
        "segment": 35,
        "quality": 7,
        "buffer_level_before": 12021,
        "buffer_level_after": 12021
      },
      {
        "start_time": 111372,
        "end_time": 114165,
        "segment": 36,
        "quality": 7,
        "buffer_level_before": 12229,
        "buffer_level_after": 12229
      },
      {
        "start_time": 114165,
        "end_time": 117329,
        "segment": 37,
        "quality": 7,
        "buffer_level_before": 12064,
        "buffer_level_after": 12064
      },
      {
        "start_time": 117329,
        "end_time": 119962,
        "segment": 38,
        "quality": 7,
        "buffer_level_before": 12431,
        "buffer_level_after": 12431
      },
      {
        "start_time": 150005,
        "end_time": 150430,
        "segment": 39,
        "quality": 0,
        "buffer_level_before": 0,
        "buffer_level_after": 0
      },
      {
        "start_time": 150430,
        "end_time": 150908,
        "segment": 40,
        "quality": 1,
        "buffer_level_before": 2522,
        "buffer_level_after": 2522
      },
      {
        "start_time": 150908,
        "end_time": 151623,
        "segment": 41,
        "quality": 2,
        "buffer_level_before": 4806,
        "buffer_level_after": 4806
      },
      {
        "start_time": 151623,
        "end_time": 153309,
        "segment": 42,
        "quality": 4,
        "buffer_level_before": 6120,
        "buffer_level_after": 6120
      },
      {
        "start_time": 153309,
        "end_time": 154668,
        "segment": 43,
        "quality": 4,
        "buffer_level_before": 7761,
        "buffer_level_after": 7761
      },
      {
        "start_time": 154668,
        "end_time": 156569,
        "segment": 44,
        "quality": 5,
        "buffer_level_before": 8860,
        "buffer_level_after": 8860
      },
      {
        "start_time": 156569,
        "end_time": 158484,
        "segment": 45,
        "quality": 5,
        "buffer_level_before": 9945,
        "buffer_level_after": 9945
      },
      {
        "start_time": 158484,
        "end_time": 161322,
        "segment": 46,
        "quality": 6,
        "buffer_level_before": 10108,
        "buffer_level_after": 10108
      },
      {
        "start_time": 161322,
        "end_time": 164021,
        "segment": 47,
        "quality": 6,
        "buffer_level_before": 10408,
        "buffer_level_after": 10408
      },
      {
        "start_time": 164021,
        "end_time": 167226,
        "segment": 48,
        "quality": 6,
        "buffer_level_before": 10204,
        "buffer_level_after": 10204
      },
      {
        "start_time": 167226,
        "end_time": 169555,
        "segment": 49,
        "quality": 6,
        "buffer_level_before": 10875,
        "buffer_level_after": 10875
      },
      {
        "start_time": 169555,
        "end_time": 172685,
        "segment": 50,
        "quality": 6,
        "buffer_level_before": 10744,
        "buffer_level_after": 10744
      },
      {
        "start_time": 172685,
        "end_time": 175454,
        "segment": 51,
        "quality": 6,
        "buffer_level_before": 10976,
        "buffer_level_after": 10976
      },
      {
        "start_time": 175454,
        "end_time": 177940,
        "segment": 52,
        "quality": 6,
        "buffer_level_before": 11489,
        "buffer_level_after": 11489
      },
      {
        "start_time": 210008,
        "end_time": 210685,
        "segment": 53,
        "quality": 0,
        "buffer_level_before": 0,
        "buffer_level_after": 0
      },
      {
        "start_time": 210685,
        "end_time": 211499,
        "segment": 54,
        "quality": 1,
        "buffer_level_before": 2186,
        "buffer_level_after": 2186
      },
      {
        "start_time": 211499,
        "end_time": 212532,
        "segment": 55,
        "quality": 2,
        "buffer_level_before": 4153,
        "buffer_level_after": 4153
      },
      {
        "start_time": 212532,
        "end_time": 214026,
        "segment": 56,
        "quality": 3,
        "buffer_level_before": 5659,
        "buffer_level_after": 5659
      },
      {
        "start_time": 214026,
        "end_time": 216315,
        "segment": 57,
        "quality": 4,
        "buffer_level_before": 6370,
        "buffer_level_after": 6370
      },
      {
        "start_time": 216315,
        "end_time": 218504,
        "segment": 58,
        "quality": 4,
        "buffer_level_before": 7181,
        "buffer_level_after": 7181
      },
      {
        "start_time": 218504,
        "end_time": 220798,
        "segment": 59,
        "quality": 5,
        "buffer_level_before": 7887,
        "buffer_level_after": 7887
      },
      {
        "start_time": 220798,
        "end_time": 224229,
        "segment": 60,
        "quality": 5,
        "buffer_level_before": 7456,
        "buffer_level_after": 7456
      },
      {
        "start_time": 224229,
        "end_time": 226928,
        "segment": 61,
        "quality": 5,
        "buffer_level_before": 7756,
        "buffer_level_after": 7756
      },
      {
        "start_time": 226928,
        "end_time": 230344,
        "segment": 62,
        "quality": 5,
        "buffer_level_before": 7341,
        "buffer_level_after": 7341
      },
      {
        "start_time": 230344,
        "end_time": 232703,
        "segment": 63,
        "quality": 5,
        "buffer_level_before": 7982,
        "buffer_level_after": 7982
      },
      {
        "start_time": 232703,
        "end_time": 236218,
        "segment": 64,
        "quality": 5,
        "buffer_level_before": 7466,
        "buffer_level_after": 7466
      },
      {
        "start_time": 236218,
        "end_time": 239064,
        "segment": 65,
        "quality": 5,
        "buffer_level_before": 7621,
        "buffer_level_after": 7621
      },
      {
        "start_time": 270013,
        "end_time": 271071,
        "segment": 66,
        "quality": 0,
        "buffer_level_before": 0,
        "buffer_level_after": 0
      },
      {
        "start_time": 271071,
        "end_time": 272261,
        "segment": 67,
        "quality": 1,
        "buffer_level_before": 1810,
        "buffer_level_after": 1810
      },
      {
        "start_time": 272261,
        "end_time": 273942,
        "segment": 68,
        "quality": 2,
        "buffer_level_before": 3129,
        "buffer_level_after": 3129
      },
      {
        "start_time": 273942,
        "end_time": 276244,
        "segment": 69,
        "quality": 3,
        "buffer_level_before": 3827,
        "buffer_level_after": 3827
      },
      {
        "start_time": 276244,
        "end_time": 278771,
        "segment": 70,
        "quality": 3,
        "buffer_level_before": 4300,
        "buffer_level_after": 4300
      },
      {
        "start_time": 278771,
        "end_time": 280759,
        "segment": 71,
        "quality": 3,
        "buffer_level_before": 5312,
        "buffer_level_after": 5312
      },
      {
        "start_time": 280759,
        "end_time": 284828,
        "segment": 72,
        "quality": 4,
        "buffer_level_before": 4242,
        "buffer_level_after": 4242
      },
      {
        "start_time": 284828,
        "end_time": 287098,
        "segment": 73,
        "quality": 3,
        "buffer_level_before": 4973,
        "buffer_level_after": 4973
      },
      {
        "start_time": 287098,
        "end_time": 291079,
        "segment": 74,
        "quality": 4,
        "buffer_level_before": 3992,
        "buffer_level_after": 3992
      },
      {
        "start_time": 291079,
        "end_time": 293092,
        "segment": 75,
        "quality": 3,
        "buffer_level_before": 4978,
        "buffer_level_after": 4978
      },
      {
        "start_time": 293092,
        "end_time": 296836,
        "segment": 76,
        "quality": 4,
        "buffer_level_before": 4235,
        "buffer_level_after": 4235
      },
      {
        "start_time": 296836,
        "end_time": 299139,
        "segment": 77,
        "quality": 3,
        "buffer_level_before": 4932,
        "buffer_level_after": 4932
      },
      {
        "start_time": 299139,
        "end_time": 302505,
        "segment": 78,
        "quality": 4,
        "buffer_level_before": 4566,
        "buffer_level_after": 4566
      },
      {
        "start_time": 302505,
        "end_time": 304365,
        "segment": 79,
        "quality": 3,
        "buffer_level_before": 5706,
        "buffer_level_after": 5706
      },
      {
        "start_time": 304365,
        "end_time": 306562,
        "segment": 80,
        "quality": 4,
        "buffer_level_before": 6509,
        "buffer_level_after": 6509
      },
      {
        "start_time": 306562,
        "end_time": 308353,
        "segment": 81,
        "quality": 4,
        "buffer_level_before": 7718,
        "buffer_level_after": 7718
      },
      {
        "start_time": 308353,
        "end_time": 312664,
        "segment": 82,
        "quality": 5,
        "buffer_level_before": 6407,
        "buffer_level_after": 6407
      },
      {
        "start_time": 312664,
        "end_time": 314850,
        "segment": 83,
        "quality": 4,
        "buffer_level_before": 7221,
        "buffer_level_after": 7221
      },
      {
        "start_time": 314850,
        "end_time": 318947,
        "segment": 84,
        "quality": 5,
        "buffer_level_before": 6124,
        "buffer_level_after": 6124
      },
      {
        "start_time": 318947,
        "end_time": 321028,
        "segment": 85,
        "quality": 4,
        "buffer_level_before": 7043,
        "buffer_level_after": 7043
      },
      {
        "start_time": 321028,
        "end_time": 324840,
        "segment": 86,
        "quality": 5,
        "buffer_level_before": 6231,
        "buffer_level_after": 6231
      },
      {
        "start_time": 324840,
        "end_time": 326908,
        "segment": 87,
        "quality": 4,
        "buffer_level_before": 7163,
        "buffer_level_after": 7163
      },
      {
        "start_time": 326908,
        "end_time": 330307,
        "segment": 88,
        "quality": 5,
        "buffer_level_before": 6764,
        "buffer_level_after": 6764
      },
      {
        "start_time": 330307,
        "end_time": 331311,
        "segment": 89,
        "quality": 4,
        "buffer_level_before": 8760,
        "buffer_level_after": 8760
      },
      {
        "start_time": 331311,
        "end_time": 332682,
        "segment": 90,
        "quality": 5,
        "buffer_level_before": 10389,
        "buffer_level_after": 10389
      },
      {
        "start_time": 332682,
        "end_time": 334040,
        "segment": 91,
        "quality": 6,
        "buffer_level_before": 12031,
        "buffer_level_after": 12031
      },
      {
        "start_time": 334040,
        "end_time": 337019,
        "segment": 92,
        "quality": 7,
        "buffer_level_before": 12051,
        "buffer_level_after": 12051
      },
      {
        "start_time": 337019,
        "end_time": 339337,
        "segment": 93,
        "quality": 7,
        "buffer_level_before": 12734,
        "buffer_level_after": 12734
      },
      {
        "start_time": 339337,
        "end_time": 342267,
        "segment": 94,
        "quality": 7,
        "buffer_level_before": 12804,
        "buffer_level_after": 12804
      },
      {
        "start_time": 342267,
        "end_time": 344181,
        "segment": 95,
        "quality": 7,
        "buffer_level_before": 13890,
        "buffer_level_after": 13890
      },
      {
        "start_time": 344181,
        "end_time": 346938,
        "segment": 96,
        "quality": 7,
        "buffer_level_before": 14133,
        "buffer_level_after": 14133
      },
      {
        "start_time": 346938,
        "end_time": 349597,
        "segment": 97,
        "quality": 7,
        "buffer_level_before": 14474,
        "buffer_level_after": 14474
      },
      {
        "start_time": 349597,
        "end_time": 353018,
        "segment": 98,
        "quality": 8,
        "buffer_level_before": 14053,
        "buffer_level_after": 14053
      },
      {
        "start_time": 353018,
        "end_time": 355366,
        "segment": 99,
        "quality": 7,
        "buffer_level_before": 14705,
        "buffer_level_after": 14705
      },
      {
        "start_time": 390004,
        "end_time": 390473,
        "segment": 100,
        "quality": 0,
        "buffer_level_before": 0,
        "buffer_level_after": 0
      },
      {
        "start_time": 390473,
        "end_time": 390606,
        "segment": 101,
        "quality": 1,
        "buffer_level_before": 2867,
        "buffer_level_after": 2867
      },
      {
        "start_time": 390606,
        "end_time": 391205,
        "segment": 102,
        "quality": 3,
        "buffer_level_before": 5268,
        "buffer_level_after": 5268
      },
      {
        "start_time": 391205,
        "end_time": 392339,
        "segment": 103,
        "quality": 4,
        "buffer_level_before": 7134,
        "buffer_level_after": 7134
      },
      {
        "start_time": 392339,
        "end_time": 393898,
        "segment": 104,
        "quality": 5,
        "buffer_level_before": 8575,
        "buffer_level_after": 8575
      },
      {
        "start_time": 393898,
        "end_time": 395298,
        "segment": 105,
        "quality": 5,
        "buffer_level_before": 10175,
        "buffer_level_after": 10175
      },
      {
        "start_time": 395298,
        "end_time": 396984,
        "segment": 106,
        "quality": 6,
        "buffer_level_before": 11489,
        "buffer_level_after": 11489
      },
      {
        "start_time": 396984,
        "end_time": 399972,
        "segment": 107,
        "quality": 7,
        "buffer_level_before": 11501,
        "buffer_level_after": 11501
      },
      {
        "start_time": 399972,
        "end_time": 402764,
        "segment": 108,
        "quality": 7,
        "buffer_level_before": 11709,
        "buffer_level_after": 11709
      },
      {
        "start_time": 402764,
        "end_time": 405569,
        "segment": 109,
        "quality": 7,
        "buffer_level_before": 11904,
        "buffer_level_after": 11904
      },
      {
        "start_time": 405569,
        "end_time": 408466,
        "segment": 110,
        "quality": 7,
        "buffer_level_before": 12007,
        "buffer_level_after": 12007
      },
      {
        "start_time": 408466,
        "end_time": 411525,
        "segment": 111,
        "quality": 7,
        "buffer_level_before": 11948,
        "buffer_level_after": 11948
      },
      {
        "start_time": 411525,
        "end_time": 414334,
        "segment": 112,
        "quality": 7,
        "buffer_level_before": 12139,
        "buffer_level_after": 12139
      },
      {
        "start_time": 414334,
        "end_time": 418290,
        "segment": 113,
        "quality": 7,
        "buffer_level_before": 11182,
        "buffer_level_after": 11182
      },
      {
        "start_time": 418290,
        "end_time": 419988,
        "segment": 114,
        "quality": 6,
        "buffer_level_before": 12485,
        "buffer_level_after": 12485
      },
      {
        "start_time": 450005,
        "end_time": 450409,
        "segment": 115,
        "quality": 0,
        "buffer_level_before": 0,
        "buffer_level_after": 0
      },
      {
        "start_time": 450409,
        "end_time": 450954,
        "segment": 116,
        "quality": 1,
        "buffer_level_before": 2454,
        "buffer_level_after": 2454
      },
      {
        "start_time": 450954,
        "end_time": 451593,
        "segment": 117,
        "quality": 2,
        "buffer_level_before": 4816,
        "buffer_level_after": 4816
      },
      {
        "start_time": 451593,
        "end_time": 453068,
        "segment": 118,
        "quality": 4,
        "buffer_level_before": 6341,
        "buffer_level_after": 6341
      },
      {
        "start_time": 453068,
        "end_time": 454557,
        "segment": 119,
        "quality": 4,
        "buffer_level_before": 7852,
        "buffer_level_after": 7852
      },
      {
        "start_time": 454557,
        "end_time": 456185,
        "segment": 120,
        "quality": 5,
        "buffer_level_before": 9224,
        "buffer_level_after": 9224
      },
      {
        "start_time": 456185,
        "end_time": 458562,
        "segment": 121,
        "quality": 5,
        "buffer_level_before": 9846,
        "buffer_level_after": 9846
      },
      {
        "start_time": 458562,
        "end_time": 461192,
        "segment": 122,
        "quality": 6,
        "buffer_level_before": 10217,
        "buffer_level_after": 10217
      },
      {
        "start_time": 461192,
        "end_time": 463987,
        "segment": 123,
        "quality": 6,
        "buffer_level_before": 10422,
        "buffer_level_after": 10422
      },
      {
        "start_time": 463987,
        "end_time": 466872,
        "segment": 124,
        "quality": 6,
        "buffer_level_before": 10537,
        "buffer_level_after": 10537
      },
      {
        "start_time": 466872,
        "end_time": 470061,
        "segment": 125,
        "quality": 6,
        "buffer_level_before": 10348,
        "buffer_level_after": 10348
      },
      {
        "start_time": 470061,
        "end_time": 472195,
        "segment": 126,
        "quality": 6,
        "buffer_level_before": 11214,
        "buffer_level_after": 11214
      },
      {
        "start_time": 472195,
        "end_time": 474814,
        "segment": 127,
        "quality": 6,
        "buffer_level_before": 11594,
        "buffer_level_after": 11594
      },
      {
        "start_time": 474814,
        "end_time": 479353,
        "segment": 128,
        "quality": 7,
        "buffer_level_before": 10056,
        "buffer_level_after": 10056
      },
      {
        "start_time": 500900,
        "end_time": 504773,
        "segment": 122,
        "quality": 6,
        "buffer_level_before": 0,
        "buffer_level_after": 0
      },
      {
        "start_time": 504773,
        "end_time": 507391,
        "segment": 123,
        "quality": 5,
        "buffer_level_before": 381,
        "buffer_level_after": 381
      },
      {
        "start_time": 507391,
        "end_time": 510553,
        "segment": 124,
        "quality": 5,
        "buffer_level_before": 219,
        "buffer_level_after": 219
      },
      {
        "start_time": 510553,
        "end_time": 512956,
        "segment": 125,
        "quality": 4,
        "buffer_level_before": 817,
        "buffer_level_after": 817
      },
      {
        "start_time": 512956,
        "end_time": 514585,
        "segment": 126,
        "quality": 4,
        "buffer_level_before": 2187,
        "buffer_level_after": 2187
      },
      {
        "start_time": 514585,
        "end_time": 516503,
        "segment": 127,
        "quality": 4,
        "buffer_level_before": 3270,
        "buffer_level_after": 3270
      },
      {
        "start_time": 516503,
        "end_time": 519866,
        "segment": 128,
        "quality": 5,
        "buffer_level_before": 2907,
        "buffer_level_after": 2907
      },
      {
        "start_time": 520200,
        "end_time": 523008,
        "segment": 175,
        "quality": 5,
        "buffer_level_before": 0,
        "buffer_level_after": 0
      },
      {
        "start_time": 523008,
        "end_time": 525185,
        "segment": 176,
        "quality": 4,
        "buffer_level_before": 823,
        "buffer_level_after": 823
      },
      {
        "start_time": 525185,
        "end_time": 527465,
        "segment": 177,
        "quality": 4,
        "buffer_level_before": 1543,
        "buffer_level_after": 1543
      },
      {
        "start_time": 554400,
        "end_time": 557645,
        "segment": 162,
        "quality": 5,
        "buffer_level_before": 0,
        "buffer_level_after": 0
      },
      {
        "start_time": 557645,
        "end_time": 560709,
        "segment": 163,
        "quality": 4,
        "buffer_level_before": 0,
        "buffer_level_after": 0
      },
      {
        "start_time": 560709,
        "end_time": 562362,
        "segment": 164,
        "quality": 3,
        "buffer_level_before": 1347,
        "buffer_level_after": 1347
      },
      {
        "start_time": 562362,
        "end_time": 565078,
        "segment": 165,
        "quality": 3,
        "buffer_level_before": 1631,
        "buffer_level_after": 1631
      },
      {
        "start_time": 565078,
        "end_time": 567152,
        "segment": 166,
        "quality": 3,
        "buffer_level_before": 2557,
        "buffer_level_after": 2557
      },
      {
        "start_time": 567152,
        "end_time": 569856,
        "segment": 167,
        "quality": 4,
        "buffer_level_before": 2853,
        "buffer_level_after": 2853
      },
      {
        "start_time": 569856,
        "end_time": 572268,
        "segment": 168,
        "quality": 3,
        "buffer_level_before": 3441,
        "buffer_level_after": 3441
      },
      {
        "start_time": 572268,
        "end_time": 574810,
        "segment": 169,
        "quality": 3,
        "buffer_level_before": 3899,
        "buffer_level_after": 3899
      },
      {
        "start_time": 574810,
        "end_time": 577093,
        "segment": 170,
        "quality": 3,
        "buffer_level_before": 4616,
        "buffer_level_after": 4616
      },
      {
        "start_time": 577093,
        "end_time": 579520,
        "segment": 171,
        "quality": 3,
        "buffer_level_before": 5189,
        "buffer_level_after": 5189
      },
      {
        "start_time": 579520,
        "end_time": 583027,
        "segment": 172,
        "quality": 4,
        "buffer_level_before": 4682,
        "buffer_level_after": 4682
      },
      {
        "start_time": 583027,
        "end_time": 584730,
        "segment": 173,
        "quality": 3,
        "buffer_level_before": 5979,
        "buffer_level_after": 5979
      },
      {
        "start_time": 584730,
        "end_time": 587219,
        "segment": 174,
        "quality": 4,
        "buffer_level_before": 6490,
        "buffer_level_after": 6490
      },
      {
        "start_time": 587219,
        "end_time": 589627,
        "segment": 175,
        "quality": 4,
        "buffer_level_before": 7082,
        "buffer_level_after": 7082
      },
      {
        "start_time": 589627,
        "end_time": 592178,
        "segment": 176,
        "quality": 4,
        "buffer_level_before": 7531,
        "buffer_level_after": 7531
      },
      {
        "start_time": 592178,
        "end_time": 595980,
        "segment": 177,
        "quality": 5,
        "buffer_level_before": 6729,
        "buffer_level_after": 6729
      },
      {
        "start_time": 595980,
        "end_time": 598249,
        "segment": 178,
        "quality": 4,
        "buffer_level_before": 7460,
        "buffer_level_after": 7460
      },
      {
        "start_time": 598249,
        "end_time": 601522,
        "segment": 179,
        "quality": 5,
        "buffer_level_before": 7187,
        "buffer_level_after": 7187
      },
      {
        "start_time": 601522,
        "end_time": 604013,
        "segment": 180,
        "quality": 4,
        "buffer_level_before": 7696,
        "buffer_level_after": 7696
      },
      {
        "start_time": 604013,
        "end_time": 607623,
        "segment": 181,
        "quality": 5,
        "buffer_level_before": 7086,
        "buffer_level_after": 7086
      },
      {
        "start_time": 607623,
        "end_time": 610070,
        "segment": 182,
        "quality": 4,
        "buffer_level_before": 7639,
        "buffer_level_after": 7639
      },
      {
        "start_time": 610070,
        "end_time": 612911,
        "segment": 183,
        "quality": 5,
        "buffer_level_before": 7798,
        "buffer_level_after": 7798
      },
      {
        "start_time": 612911,
        "end_time": 614343,
        "segment": 184,
        "quality": 5,
        "buffer_level_before": 9366,
        "buffer_level_after": 9366
      },
      {
        "start_time": 614343,
        "end_time": 615621,
        "segment": 185,
        "quality": 5,
        "buffer_level_before": 11087,
        "buffer_level_after": 11087
      },
      {
        "start_time": 615621,
        "end_time": 617374,
        "segment": 186,
        "quality": 6,
        "buffer_level_before": 12335,
        "buffer_level_after": 12335
      },
      {
        "start_time": 617374,
        "end_time": 619949,
        "segment": 187,
        "quality": 7,
        "buffer_level_before": 12760,
        "buffer_level_after": 12760
      },
      {
        "start_time": 619949,
        "end_time": 622582,
        "segment": 188,
        "quality": 7,
        "buffer_level_before": 13127,
        "buffer_level_after": 13127
      },
      {
        "start_time": 622582,
        "end_time": 625837,
        "segment": 189,
        "quality": 7,
        "buffer_level_before": 12872,
        "buffer_level_after": 12872
      },
      {
        "start_time": 625837,
        "end_time": 627690,
        "segment": 190,
        "quality": 7,
        "buffer_level_before": 14019,
        "buffer_level_after": 14019
      },
      {
        "start_time": 627690,
        "end_time": 630023,
        "segment": 191,
        "quality": 7,
        "buffer_level_before": 14686,
        "buffer_level_after": 14686
      },
      {
        "start_time": 630023,
        "end_time": 634217,
        "segment": 192,
        "quality": 8,
        "buffer_level_before": 13492,
        "buffer_level_after": 13492
      },
      {
        "start_time": 634217,
        "end_time": 636442,
        "segment": 193,
        "quality": 7,
        "buffer_level_before": 14267,
        "buffer_level_after": 14267
      },
      {
        "start_time": 636442,
        "end_time": 638899,
        "segment": 194,
        "quality": 7,
        "buffer_level_before": 14810,
        "buffer_level_after": 14810
      },
      {
        "start_time": 638899,
        "end_time": 673189,
        "segment": 195,
        "quality": 8,
        "buffer_level_before": 0,
        "buffer_level_after": 0
      },
      {
        "start_time": 673189,
        "end_time": 673456,
        "segment": 196,
        "quality": 0,
        "buffer_level_before": 2733,
        "buffer_level_after": 2733
      },
      {
        "start_time": 673456,
        "end_time": 673717,
        "segment": 197,
        "quality": 0,
        "buffer_level_before": 5472,
        "buffer_level_after": 5472
      },
      {
        "start_time": 673717,
        "end_time": 673946,
        "segment": 198,
        "quality": 0,
        "buffer_level_before": 8243,
        "buffer_level_after": 8243
      }
    ],
    "prefetch_events": [],
    "seek_events": [
      {
        "seek_to_s": 365,
        "segment": 122
      },
      {
        "seek_to_s": 524,
        "segment": 175
      },
      {
        "seek_to_s": 485,
        "segment": 162
      }
    ],
    "time_series": {
      "time_points": [
        0.804,
        3.102,
        4.987,
        8.088,
        10.269,
        13.282,
        16.026,
        19.243,
        21.257,
        23.661,
        26.281,
        28.74,
        30.748,
        32.161,
        34.045,
        35.764,
        38.019,
        40.962,
        43.151,
        46.285,
        48.887,
        53.261,
        55.514,
        58.454,
        90.394,
        90.907,
        91.586,
        92.607,
        93.921,
        96.21,
        98.024,
        99.994,
        102.561,
        106.074,
        108.134,
        111.372,
        114.165,
        117.329,
        119.962,
        150.43,
        150.908,
        151.623,
        153.309,
        154.668,
        156.569,
        158.484,
        161.322,
        164.021,
        167.226,
        169.555,
        172.685,
        175.454,
        177.94,
        210.685,
        211.499,
        212.532,
        214.026,
        216.315,
        218.504,
        220.798,
        224.229,
        226.928,
        230.344,
        232.703,
        236.218,
        239.064,
        271.071,
        272.261,
        273.942,
        276.244,
        278.771,
        280.759,
        284.828,
        287.098,
        291.079,
        293.092,
        296.836,
        299.139,
        302.505,
        304.365,
        306.562,
        308.353,
        312.664,
        314.85,
        318.947,
        321.028,
        324.84,
        326.908,
        330.307,
        331.311,
        332.682,
        334.04,
        337.019,
        339.337,
        342.267,
        344.181,
        346.938,
        349.597,
        353.018,
        355.366,
        390.473,
        390.606,
        391.205,
        392.339,
        393.898,
        395.298,
        396.984,
        399.972,
        402.764,
        405.569,
        408.466,
        411.525,
        414.334,
        418.29,
        419.988,
        450.409,
        450.954,
        451.593,
        453.068,
        454.557,
        456.185,
        458.562,
        461.192,
        463.987,
        466.872,
        470.061,
        472.195,
        474.814,
        479.353,
        504.773,
        507.391,
        510.553,
        512.956,
        514.585,
        516.503,
        519.866,
        523.008,
        525.185,
        527.465,
        557.645,
        560.709,
        562.362,
        565.078,
        567.152,
        569.856,
        572.268,
        574.81,
        577.093,
        579.52,
        583.027,
        584.73,
        587.219,
        589.627,
        592.178,
        595.98,
        598.249,
        601.522,
        604.013,
        607.623,
        610.07,
        612.911,
        614.343,
        615.621,
        617.374,
        619.949,
        622.582,
        625.837,
        627.69,
        630.023,
        634.217,
        636.442,
        638.899,
        673.189,
        673.456,
        673.717,
        673.946
      ],
      "buffer_levels": [
        0.0,
        0.702,
        1.817,
        1.716,
        2.535,
        2.521,
        2.777,
        2.56,
        3.547,
        4.142,
        4.523,
        5.064,
        6.056,
        7.643,
        8.758,
        10.04,
        10.785,
        10.842,
        11.653,
        11.519,
        11.917,
        10.543,
        11.29,
        11.349,
        0.0,
        2.487,
        4.808,
        6.786,
        8.472,
        9.183,
        10.37,
        11.4,
        11.833,
        11.32,
        12.26,
        12.021,
        12.229,
        12.064,
        12.431,
        0.0,
        2.522,
        4.806,
        6.12,
        7.761,
        8.86,
        9.945,
        10.108,
        10.408,
        10.204,
        10.875,
        10.744,
        10.976,
        11.489,
        0.0,
        2.186,
        4.153,
        5.659,
        6.37,
        7.181,
        7.887,
        7.456,
        7.756,
        7.341,
        7.982,
        7.466,
        7.621,
        0.0,
        1.81,
        3.129,
        3.827,
        4.3,
        5.312,
        4.242,
        4.973,
        3.992,
        4.978,
        4.235,
        4.932,
        4.566,
        5.706,
        6.509,
        7.718,
        6.407,
        7.221,
        6.124,
        7.043,
        6.231,
        7.163,
        6.764,
        8.76,
        10.389,
        12.031,
        12.051,
        12.734,
        12.804,
        13.89,
        14.133,
        14.474,
        14.053,
        14.705,
        0.0,
        2.867,
        5.268,
        7.134,
        8.575,
        10.175,
        11.489,
        11.501,
        11.709,
        11.904,
        12.007,
        11.948,
        12.139,
        11.182,
        12.485,
        0.0,
        2.454,
        4.816,
        6.341,
        7.852,
        9.224,
        9.846,
        10.217,
        10.422,
        10.537,
        10.348,
        11.214,
        11.594,
        10.056,
        0.0,
        0.381,
        0.219,
        0.817,
        2.187,
        3.27,
        2.907,
        0.0,
        0.823,
        1.543,
        0.0,
        0.0,
        1.347,
        1.631,
        2.557,
        2.853,
        3.441,
        3.899,
        4.616,
        5.189,
        4.682,
        5.979,
        6.49,
        7.082,
        7.531,
        6.729,
        7.46,
        7.187,
        7.696,
        7.086,
        7.639,
        7.798,
        9.366,
        11.087,
        12.335,
        12.76,
        13.127,
        12.872,
        14.019,
        14.686,
        13.492,
        14.267,
        14.81,
        0.0,
        2.733,
        5.472,
        8.243
      ],
      "qualities": [
        0,
        4,
        4,
        4,
        4,
        5,
        4,
        4,
        4,
        4,
        4,
        4,
        5,
        5,
        6,
        6,
        7,
        7,
        7,
        7,
        7,
        8,
        7,
        7,
        1,
        2,
        3,
        4,
        5,
        6,
        6,
        6,
        7,
        7,
        7,
        7,
        7,
        7,
        7,
        0,
        1,
        2,
        4,
        4,
        5,
        5,
        6,
        6,
        6,
        6,
        6,
        6,
        6,
        0,
        1,
        2,
        3,
        4,
        4,
        5,
        5,
        5,
        5,
        5,
        5,
        5,
        0,
        1,
        2,
        3,
        3,
        3,
        4,
        3,
        4,
        3,
        4,
        3,
        4,
        3,
        4,
        4,
        5,
        4,
        5,
        4,
        5,
        4,
        5,
        4,
        5,
        6,
        7,
        7,
        7,
        7,
        7,
        7,
        8,
        7,
        0,
        1,
        3,
        4,
        5,
        5,
        6,
        7,
        7,
        7,
        7,
        7,
        7,
        7,
        6,
        0,
        1,
        2,
        4,
        4,
        5,
        5,
        6,
        6,
        6,
        6,
        6,
        6,
        7,
        6,
        5,
        5,
        4,
        4,
        4,
        5,
        5,
        4,
        4,
        5,
        4,
        3,
        3,
        3,
        4,
        3,
        3,
        3,
        3,
        4,
        3,
        4,
        4,
        4,
        5,
        4,
        5,
        4,
        5,
        4,
        5,
        5,
        5,
        6,
        7,
        7,
        7,
        7,
        7,
        8,
        7,
        7,
        8,
        0,
        0,
        0
      ],
      "segments": [
        0,
        1,
        2,
        3,
        4,
        5,
        6,
        7,
        8,
        9,
        10,
        11,
        12,
        13,
        14,
        15,
        16,
        17,
        18,
        19,
        20,
        21,
        22,
        23,
        24,
        25,
        26,
        27,
        28,
        29,
        30,
        31,
        32,
        33,
        34,
        35,
        36,
        37,
        38,
        39,
        40,
        41,
        42,
        43,
        44,
        45,
        46,
        47,
        48,
        49,
        50,
        51,
        52,
        53,
        54,
        55,
        56,
        57,
        58,
        59,
        60,
        61,
        62,
        63,
        64,
        65,
        66,
        67,
        68,
        69,
        70,
        71,
        72,
        73,
        74,
        75,
        76,
        77,
        78,
        79,
        80,
        81,
        82,
        83,
        84,
        85,
        86,
        87,
        88,
        89,
        90,
        91,
        92,
        93,
        94,
        95,
        96,
        97,
        98,
        99,
        100,
        101,
        102,
        103,
        104,
        105,
        106,
        107,
        108,
        109,
        110,
        111,
        112,
        113,
        114,
        115,
        116,
        117,
        118,
        119,
        120,
        121,
        122,
        123,
        124,
        125,
        126,
        127,
        128,
        122,
        123,
        124,
        125,
        126,
        127,
        128,
        175,
        176,
        177,
        162,
        163,
        164,
        165,
        166,
        167,
        168,
        169,
        170,
        171,
        172,
        173,
        174,
        175,
        176,
        177,
        178,
        179,
        180,
        181,
        182,
        183,
        184,
        185,
        186,
        187,
        188,
        189,
        190,
        191,
        192,
        193,
        194,
        195,
        196,
        197,
        198
      ]
    }
  },
  "with_buffer_py": {
    "summary": {
      "played_utility": 300.026425,
      "played_bitrate": 280139.0,
      "total_play_time": 685.189212,
      "total_rebuffer_time": 176.795597,
      "rebuffer_ratio": 0.258024,
      "rebuffer_count": 17,
      "rampup_time": 3.2452
    },
    "download_events": [
      {
        "start_time": 0,
        "end_time": 804,
        "segment": 0,
        "quality": 0,
        "buffer_level_before": 0,
        "buffer_level_after": 0
      },
      {
        "start_time": 804,
        "end_time": 3102,
        "segment": 1,
        "quality": 4,
        "buffer_level_before": 702,
        "buffer_level_after": 702
      },
      {
        "start_time": 3102,
        "end_time": 4987,
        "segment": 2,
        "quality": 4,
        "buffer_level_before": 1817,
        "buffer_level_after": 1817
      },
      {
        "start_time": 4987,
        "end_time": 8088,
        "segment": 3,
        "quality": 4,
        "buffer_level_before": 1716,
        "buffer_level_after": 1716
      },
      {
        "start_time": 8088,
        "end_time": 10269,
        "segment": 4,
        "quality": 4,
        "buffer_level_before": 2535,
        "buffer_level_after": 2535
      },
      {
        "start_time": 10269,
        "end_time": 13282,
        "segment": 5,
        "quality": 5,
        "buffer_level_before": 2521,
        "buffer_level_after": 2521
      },
      {
        "start_time": 13282,
        "end_time": 16026,
        "segment": 6,
        "quality": 4,
        "buffer_level_before": 2777,
        "buffer_level_after": 2777
      },
      {
        "start_time": 16026,
        "end_time": 19243,
        "segment": 7,
        "quality": 4,
        "buffer_level_before": 2560,
        "buffer_level_after": 2560
      },
      {
        "start_time": 19243,
        "end_time": 21257,
        "segment": 8,
        "quality": 4,
        "buffer_level_before": 3547,
        "buffer_level_after": 3547
      },
      {
        "start_time": 21257,
        "end_time": 23661,
        "segment": 9,
        "quality": 4,
        "buffer_level_before": 4142,
        "buffer_level_after": 4142
      },
      {
        "start_time": 23661,
        "end_time": 26281,
        "segment": 10,
        "quality": 4,
        "buffer_level_before": 4523,
        "buffer_level_after": 4523
      },
      {
        "start_time": 26281,
        "end_time": 28740,
        "segment": 11,
        "quality": 4,
        "buffer_level_before": 5064,
        "buffer_level_after": 5064
      },
      {
        "start_time": 28740,
        "end_time": 30748,
        "segment": 12,
        "quality": 5,
        "buffer_level_before": 6056,
        "buffer_level_after": 6056
      },
      {
        "start_time": 30748,
        "end_time": 32161,
        "segment": 13,
        "quality": 5,
        "buffer_level_before": 7643,
        "buffer_level_after": 7643
      },
      {
        "start_time": 32161,
        "end_time": 34045,
        "segment": 14,
        "quality": 6,
        "buffer_level_before": 8758,
        "buffer_level_after": 8758
      },
      {
        "start_time": 34045,
        "end_time": 35764,
        "segment": 15,
        "quality": 6,
        "buffer_level_before": 10040,
        "buffer_level_after": 10040
      },
      {
        "start_time": 35764,
        "end_time": 38019,
        "segment": 16,
        "quality": 7,
        "buffer_level_before": 10785,
        "buffer_level_after": 10785
      },
      {
        "start_time": 38019,
        "end_time": 40962,
        "segment": 17,
        "quality": 7,
        "buffer_level_before": 10842,
        "buffer_level_after": 10842
      },
      {
        "start_time": 40962,
        "end_time": 43151,
        "segment": 18,
        "quality": 7,
        "buffer_level_before": 11653,
        "buffer_level_after": 11653
      },
      {
        "start_time": 43151,
        "end_time": 46285,
        "segment": 19,
        "quality": 7,
        "buffer_level_before": 11519,
        "buffer_level_after": 11519
      },
      {
        "start_time": 46285,
        "end_time": 48887,
        "segment": 20,
        "quality": 7,
        "buffer_level_before": 11917,
        "buffer_level_after": 11917
      },
      {
        "start_time": 48887,
        "end_time": 53261,
        "segment": 21,
        "quality": 8,
        "buffer_level_before": 10543,
        "buffer_level_after": 10543
      },
      {
        "start_time": 53261,
        "end_time": 55514,
        "segment": 22,
        "quality": 7,
        "buffer_level_before": 11290,
        "buffer_level_after": 11290
      },
      {
        "start_time": 55514,
        "end_time": 58454,
        "segment": 23,
        "quality": 7,
        "buffer_level_before": 11349,
        "buffer_level_after": 11349
      },
      {
        "start_time": 90004,
        "end_time": 90394,
        "segment": 24,
        "quality": 1,
        "buffer_level_before": 0,
        "buffer_level_after": 0
      },
      {
        "start_time": 90394,
        "end_time": 90907,
        "segment": 25,
        "quality": 2,
        "buffer_level_before": 2487,
        "buffer_level_after": 2487
      },
      {
        "start_time": 90907,
        "end_time": 91586,
        "segment": 26,
        "quality": 3,
        "buffer_level_before": 4808,
        "buffer_level_after": 4808
      },
      {
        "start_time": 91586,
        "end_time": 92607,
        "segment": 27,
        "quality": 4,
        "buffer_level_before": 6786,
        "buffer_level_after": 6786
      },
      {
        "start_time": 92607,
        "end_time": 93921,
        "segment": 28,
        "quality": 5,
        "buffer_level_before": 8472,
        "buffer_level_after": 8472
      },
      {
        "start_time": 93921,
        "end_time": 96210,
        "segment": 29,
        "quality": 6,
        "buffer_level_before": 9183,
        "buffer_level_after": 9183
      },
      {
        "start_time": 96210,
        "end_time": 98024,
        "segment": 30,
        "quality": 6,
        "buffer_level_before": 10370,
        "buffer_level_after": 10370
      },
      {
        "start_time": 98024,
        "end_time": 99994,
        "segment": 31,
        "quality": 6,
        "buffer_level_before": 11400,
        "buffer_level_after": 11400
      },
      {
        "start_time": 99994,
        "end_time": 102561,
        "segment": 32,
        "quality": 7,
        "buffer_level_before": 11833,
        "buffer_level_after": 11833
      },
      {
        "start_time": 102561,
        "end_time": 106074,
        "segment": 33,
        "quality": 7,
        "buffer_level_before": 11320,
        "buffer_level_after": 11320
      },
      {
        "start_time": 106074,
        "end_time": 108134,
        "segment": 34,
        "quality": 7,
        "buffer_level_before": 12260,
        "buffer_level_after": 12260
      },
      {
        "start_time": 108134,
        "end_time": 111372,
        "segment": 35,
        "quality": 7,
        "buffer_level_before": 12021,
        "buffer_level_after": 12021
      },
      {
        "start_time": 111372,
        "end_time": 114165,
        "segment": 36,
        "quality": 7,
        "buffer_level_before": 12229,
        "buffer_level_after": 12229
      },
      {
        "start_time": 114165,
        "end_time": 117329,
        "segment": 37,
        "quality": 7,
        "buffer_level_before": 12064,
        "buffer_level_after": 12064
      },
      {
        "start_time": 117329,
        "end_time": 119962,
        "segment": 38,
        "quality": 7,
        "buffer_level_before": 12431,
        "buffer_level_after": 12431
      },
      {
        "start_time": 150005,
        "end_time": 150430,
        "segment": 39,
        "quality": 0,
        "buffer_level_before": 0,
        "buffer_level_after": 0
      },
      {
        "start_time": 150430,
        "end_time": 150908,
        "segment": 40,
        "quality": 1,
        "buffer_level_before": 2522,
        "buffer_level_after": 2522
      },
      {
        "start_time": 150908,
        "end_time": 151623,
        "segment": 41,
        "quality": 2,
        "buffer_level_before": 4806,
        "buffer_level_after": 4806
      },
      {
        "start_time": 151623,
        "end_time": 153309,
        "segment": 42,
        "quality": 4,
        "buffer_level_before": 6120,
        "buffer_level_after": 6120
      },
      {
        "start_time": 153309,
        "end_time": 154668,
        "segment": 43,
        "quality": 4,
        "buffer_level_before": 7761,
        "buffer_level_after": 7761
      },
      {
        "start_time": 154668,
        "end_time": 156569,
        "segment": 44,
        "quality": 5,
        "buffer_level_before": 8860,
        "buffer_level_after": 8860
      },
      {
        "start_time": 156569,
        "end_time": 158484,
        "segment": 45,
        "quality": 5,
        "buffer_level_before": 9945,
        "buffer_level_after": 9945
      },
      {
        "start_time": 158484,
        "end_time": 161322,
        "segment": 46,
        "quality": 6,
        "buffer_level_before": 10108,
        "buffer_level_after": 10108
      },
      {
        "start_time": 161322,
        "end_time": 164021,
        "segment": 47,
        "quality": 6,
        "buffer_level_before": 10408,
        "buffer_level_after": 10408
      },
      {
        "start_time": 164021,
        "end_time": 167226,
        "segment": 48,
        "quality": 6,
        "buffer_level_before": 10204,
        "buffer_level_after": 10204
      },
      {
        "start_time": 167226,
        "end_time": 169555,
        "segment": 49,
        "quality": 6,
        "buffer_level_before": 10875,
        "buffer_level_after": 10875
      },
      {
        "start_time": 169555,
        "end_time": 172685,
        "segment": 50,
        "quality": 6,
        "buffer_level_before": 10744,
        "buffer_level_after": 10744
      },
      {
        "start_time": 172685,
        "end_time": 175454,
        "segment": 51,
        "quality": 6,
        "buffer_level_before": 10976,
        "buffer_level_after": 10976
      },
      {
        "start_time": 175454,
        "end_time": 177940,
        "segment": 52,
        "quality": 6,
        "buffer_level_before": 11489,
        "buffer_level_after": 11489
      },
      {
        "start_time": 210008,
        "end_time": 210685,
        "segment": 53,
        "quality": 0,
        "buffer_level_before": 0,
        "buffer_level_after": 0
      },
      {
        "start_time": 210685,
        "end_time": 211499,
        "segment": 54,
        "quality": 1,
        "buffer_level_before": 2186,
        "buffer_level_after": 2186
      },
      {
        "start_time": 211499,
        "end_time": 212532,
        "segment": 55,
        "quality": 2,
        "buffer_level_before": 4153,
        "buffer_level_after": 4153
      },
      {
        "start_time": 212532,
        "end_time": 214026,
        "segment": 56,
        "quality": 3,
        "buffer_level_before": 5659,
        "buffer_level_after": 5659
      },
      {
        "start_time": 214026,
        "end_time": 216315,
        "segment": 57,
        "quality": 4,
        "buffer_level_before": 6370,
        "buffer_level_after": 6370
      },
      {
        "start_time": 216315,
        "end_time": 218504,
        "segment": 58,
        "quality": 4,
        "buffer_level_before": 7181,
        "buffer_level_after": 7181
      },
      {
        "start_time": 218504,
        "end_time": 220798,
        "segment": 59,
        "quality": 5,
        "buffer_level_before": 7887,
        "buffer_level_after": 7887
      },
      {
        "start_time": 220798,
        "end_time": 224229,
        "segment": 60,
        "quality": 5,
        "buffer_level_before": 7456,
        "buffer_level_after": 7456
      },
      {
        "start_time": 224229,
        "end_time": 226928,
        "segment": 61,
        "quality": 5,
        "buffer_level_before": 7756,
        "buffer_level_after": 7756
      },
      {
        "start_time": 226928,
        "end_time": 230344,
        "segment": 62,
        "quality": 5,
        "buffer_level_before": 7341,
        "buffer_level_after": 7341
      },
      {
        "start_time": 230344,
        "end_time": 232703,
        "segment": 63,
        "quality": 5,
        "buffer_level_before": 7982,
        "buffer_level_after": 7982
      },
      {
        "start_time": 232703,
        "end_time": 236218,
        "segment": 64,
        "quality": 5,
        "buffer_level_before": 7466,
        "buffer_level_after": 7466
      },
      {
        "start_time": 236218,
        "end_time": 239064,
        "segment": 65,
        "quality": 5,
        "buffer_level_before": 7621,
        "buffer_level_after": 7621
      },
      {
        "start_time": 270013,
        "end_time": 271071,
        "segment": 66,
        "quality": 0,
        "buffer_level_before": 0,
        "buffer_level_after": 0
      },
      {
        "start_time": 271071,
        "end_time": 272261,
        "segment": 67,
        "quality": 1,
        "buffer_level_before": 1810,
        "buffer_level_after": 1810
      },
      {
        "start_time": 272261,
        "end_time": 273942,
        "segment": 68,
        "quality": 2,
        "buffer_level_before": 3129,
        "buffer_level_after": 3129
      },
      {
        "start_time": 273942,
        "end_time": 276244,
        "segment": 69,
        "quality": 3,
        "buffer_level_before": 3827,
        "buffer_level_after": 3827
      },
      {
        "start_time": 276244,
        "end_time": 278771,
        "segment": 70,
        "quality": 3,
        "buffer_level_before": 4300,
        "buffer_level_after": 4300
      },
      {
        "start_time": 278771,
        "end_time": 280759,
        "segment": 71,
        "quality": 3,
        "buffer_level_before": 5312,
        "buffer_level_after": 5312
      },
      {
        "start_time": 280759,
        "end_time": 284828,
        "segment": 72,
        "quality": 4,
        "buffer_level_before": 4242,
        "buffer_level_after": 4242
      },
      {
        "start_time": 284828,
        "end_time": 287098,
        "segment": 73,
        "quality": 3,
        "buffer_level_before": 4973,
        "buffer_level_after": 4973
      },
      {
        "start_time": 287098,
        "end_time": 291079,
        "segment": 74,
        "quality": 4,
        "buffer_level_before": 3992,
        "buffer_level_after": 3992
      },
      {
        "start_time": 291079,
        "end_time": 293092,
        "segment": 75,
        "quality": 3,
        "buffer_level_before": 4978,
        "buffer_level_after": 4978
      },
      {
        "start_time": 293092,
        "end_time": 296836,
        "segment": 76,
        "quality": 4,
        "buffer_level_before": 4235,
        "buffer_level_after": 4235
      },
      {
        "start_time": 296836,
        "end_time": 299139,
        "segment": 77,
        "quality": 3,
        "buffer_level_before": 4932,
        "buffer_level_after": 4932
      },
      {
        "start_time": 299139,
        "end_time": 302505,
        "segment": 78,
        "quality": 4,
        "buffer_level_before": 4566,
        "buffer_level_after": 4566
      },
      {
        "start_time": 302505,
        "end_time": 304365,
        "segment": 79,
        "quality": 3,
        "buffer_level_before": 5706,
        "buffer_level_after": 5706
      },
      {
        "start_time": 304365,
        "end_time": 306562,
        "segment": 80,
        "quality": 4,
        "buffer_level_before": 6509,
        "buffer_level_after": 6509
      },
      {
        "start_time": 306562,
        "end_time": 308353,
        "segment": 81,
        "quality": 4,
        "buffer_level_before": 7718,
        "buffer_level_after": 7718
      },
      {
        "start_time": 308353,
        "end_time": 312664,
        "segment": 82,
        "quality": 5,
        "buffer_level_before": 6407,
        "buffer_level_after": 6407
      },
      {
        "start_time": 312664,
        "end_time": 314850,
        "segment": 83,
        "quality": 4,
        "buffer_level_before": 7221,
        "buffer_level_after": 7221
      },
      {
        "start_time": 314850,
        "end_time": 318947,
        "segment": 84,
        "quality": 5,
        "buffer_level_before": 6124,
        "buffer_level_after": 6124
      },
      {
        "start_time": 318947,
        "end_time": 321028,
        "segment": 85,
        "quality": 4,
        "buffer_level_before": 7043,
        "buffer_level_after": 7043
      },
      {
        "start_time": 321028,
        "end_time": 324840,
        "segment": 86,
        "quality": 5,
        "buffer_level_before": 6231,
        "buffer_level_after": 6231
      },
      {
        "start_time": 324840,
        "end_time": 326908,
        "segment": 87,
        "quality": 4,
        "buffer_level_before": 7163,
        "buffer_level_after": 7163
      },
      {
        "start_time": 326908,
        "end_time": 330307,
        "segment": 88,
        "quality": 5,
        "buffer_level_before": 6764,
        "buffer_level_after": 6764
      },
      {
        "start_time": 330307,
        "end_time": 331311,
        "segment": 89,
        "quality": 4,
        "buffer_level_before": 8760,
        "buffer_level_after": 8760
      },
      {
        "start_time": 331311,
        "end_time": 332682,
        "segment": 90,
        "quality": 5,
        "buffer_level_before": 10389,
        "buffer_level_after": 10389
      },
      {
        "start_time": 332682,
        "end_time": 334040,
        "segment": 91,
        "quality": 6,
        "buffer_level_before": 12031,
        "buffer_level_after": 12031
      },
      {
        "start_time": 334040,
        "end_time": 337019,
        "segment": 92,
        "quality": 7,
        "buffer_level_before": 12051,
        "buffer_level_after": 12051
      },
      {
        "start_time": 337019,
        "end_time": 339337,
        "segment": 93,
        "quality": 7,
        "buffer_level_before": 12734,
        "buffer_level_after": 12734
      },
      {
        "start_time": 339337,
        "end_time": 342267,
        "segment": 94,
        "quality": 7,
        "buffer_level_before": 12804,
        "buffer_level_after": 12804
      },
      {
        "start_time": 342267,
        "end_time": 344181,
        "segment": 95,
        "quality": 7,
        "buffer_level_before": 13890,
        "buffer_level_after": 13890
      },
      {
        "start_time": 344181,
        "end_time": 346938,
        "segment": 96,
        "quality": 7,
        "buffer_level_before": 14133,
        "buffer_level_after": 14133
      },
      {
        "start_time": 346938,
        "end_time": 349597,
        "segment": 97,
        "quality": 7,
        "buffer_level_before": 14474,
        "buffer_level_after": 14474
      },
      {
        "start_time": 349597,
        "end_time": 353018,
        "segment": 98,
        "quality": 8,
        "buffer_level_before": 14053,
        "buffer_level_after": 14053
      },
      {
        "start_time": 353018,
        "end_time": 355366,
        "segment": 99,
        "quality": 7,
        "buffer_level_before": 14705,
        "buffer_level_after": 14705
      },
      {
        "start_time": 390004,
        "end_time": 390473,
        "segment": 100,
        "quality": 0,
        "buffer_level_before": 0,
        "buffer_level_after": 0
      },
      {
        "start_time": 390473,
        "end_time": 390606,
        "segment": 101,
        "quality": 1,
        "buffer_level_before": 2867,
        "buffer_level_after": 2867
      },
      {
        "start_time": 390606,
        "end_time": 391205,
        "segment": 102,
        "quality": 3,
        "buffer_level_before": 5268,
        "buffer_level_after": 5268
      },
      {
        "start_time": 391205,
        "end_time": 392339,
        "segment": 103,
        "quality": 4,
        "buffer_level_before": 7134,
        "buffer_level_after": 7134
      },
      {
        "start_time": 392339,
        "end_time": 393898,
        "segment": 104,
        "quality": 5,
        "buffer_level_before": 8575,
        "buffer_level_after": 8575
      },
      {
        "start_time": 393898,
        "end_time": 395298,
        "segment": 105,
        "quality": 5,
        "buffer_level_before": 10175,
        "buffer_level_after": 10175
      },
      {
        "start_time": 395298,
        "end_time": 396984,
        "segment": 106,
        "quality": 6,
        "buffer_level_before": 11489,
        "buffer_level_after": 11489
      },
      {
        "start_time": 396984,
        "end_time": 399972,
        "segment": 107,
        "quality": 7,
        "buffer_level_before": 11501,
        "buffer_level_after": 11501
      },
      {
        "start_time": 399972,
        "end_time": 402764,
        "segment": 108,
        "quality": 7,
        "buffer_level_before": 11709,
        "buffer_level_after": 11709
      },
      {
        "start_time": 402764,
        "end_time": 405569,
        "segment": 109,
        "quality": 7,
        "buffer_level_before": 11904,
        "buffer_level_after": 11904
      },
      {
        "start_time": 405569,
        "end_time": 408466,
        "segment": 110,
        "quality": 7,
        "buffer_level_before": 12007,
        "buffer_level_after": 12007
      },
      {
        "start_time": 408466,
        "end_time": 411525,
        "segment": 111,
        "quality": 7,
        "buffer_level_before": 11948,
        "buffer_level_after": 11948
      },
      {
        "start_time": 411525,
        "end_time": 414334,
        "segment": 112,
        "quality": 7,
        "buffer_level_before": 12139,
        "buffer_level_after": 12139
      },
      {
        "start_time": 414334,
        "end_time": 418290,
        "segment": 113,
        "quality": 7,
        "buffer_level_before": 11182,
        "buffer_level_after": 11182
      },
      {
        "start_time": 418290,
        "end_time": 419988,
        "segment": 114,
        "quality": 6,
        "buffer_level_before": 12485,
        "buffer_level_after": 12485
      },
      {
        "start_time": 450005,
        "end_time": 450409,
        "segment": 115,
        "quality": 0,
        "buffer_level_before": 0,
        "buffer_level_after": 0
      },
      {
        "start_time": 450409,
        "end_time": 450954,
        "segment": 116,
        "quality": 1,
        "buffer_level_before": 2454,
        "buffer_level_after": 2454
      },
      {
        "start_time": 450954,
        "end_time": 451593,
        "segment": 117,
        "quality": 2,
        "buffer_level_before": 4816,
        "buffer_level_after": 4816
      },
      {
        "start_time": 451593,
        "end_time": 453068,
        "segment": 118,
        "quality": 4,
        "buffer_level_before": 6341,
        "buffer_level_after": 6341
      },
      {
        "start_time": 453068,
        "end_time": 454557,
        "segment": 119,
        "quality": 4,
        "buffer_level_before": 7852,
        "buffer_level_after": 7852
      },
      {
        "start_time": 454557,
        "end_time": 456185,
        "segment": 120,
        "quality": 5,
        "buffer_level_before": 9224,
        "buffer_level_after": 9224
      },
      {
        "start_time": 456185,
        "end_time": 458562,
        "segment": 121,
        "quality": 5,
        "buffer_level_before": 9846,
        "buffer_level_after": 9846
      },
      {
        "start_time": 458562,
        "end_time": 461192,
        "segment": 122,
        "quality": 6,
        "buffer_level_before": 10217,
        "buffer_level_after": 10217
      },
      {
        "start_time": 461192,
        "end_time": 463987,
        "segment": 123,
        "quality": 6,
        "buffer_level_before": 10422,
        "buffer_level_after": 10422
      },
      {
        "start_time": 463987,
        "end_time": 466872,
        "segment": 124,
        "quality": 6,
        "buffer_level_before": 10537,
        "buffer_level_after": 10537
      },
      {
        "start_time": 466872,
        "end_time": 470061,
        "segment": 125,
        "quality": 6,
        "buffer_level_before": 10348,
        "buffer_level_after": 10348
      },
      {
        "start_time": 470061,
        "end_time": 472195,
        "segment": 126,
        "quality": 6,
        "buffer_level_before": 11214,
        "buffer_level_after": 11214
      },
      {
        "start_time": 472195,
        "end_time": 474814,
        "segment": 127,
        "quality": 6,
        "buffer_level_before": 11594,
        "buffer_level_after": 11594
      },
      {
        "start_time": 474814,
        "end_time": 479353,
        "segment": 128,
        "quality": 7,
        "buffer_level_before": 10056,
        "buffer_level_after": 10056
      },
      {
        "start_time": 500900,
        "end_time": 504773,
        "segment": 122,
        "quality": 6,
        "buffer_level_before": 0,
        "buffer_level_after": 0
      },
      {
        "start_time": 504773,
        "end_time": 507391,
        "segment": 123,
        "quality": 5,
        "buffer_level_before": 381,
        "buffer_level_after": 381
      },
      {
        "start_time": 507391,
        "end_time": 510553,
        "segment": 124,
        "quality": 5,
        "buffer_level_before": 219,
        "buffer_level_after": 219
      },
      {
        "start_time": 510553,
        "end_time": 512956,
        "segment": 125,
        "quality": 4,
        "buffer_level_before": 817,
        "buffer_level_after": 817
      },
      {
        "start_time": 512956,
        "end_time": 514585,
        "segment": 126,
        "quality": 4,
        "buffer_level_before": 2187,
        "buffer_level_after": 2187
      },
      {
        "start_time": 514585,
        "end_time": 516503,
        "segment": 127,
        "quality": 4,
        "buffer_level_before": 3270,
        "buffer_level_after": 3270
      },
      {
        "start_time": 516503,
        "end_time": 519866,
        "segment": 128,
        "quality": 5,
        "buffer_level_before": 2907,
        "buffer_level_after": 2907
      },
      {
        "start_time": 520200,
        "end_time": 523008,
        "segment": 175,
        "quality": 5,
        "buffer_level_before": 0,
        "buffer_level_after": 0
      },
      {
        "start_time": 523008,
        "end_time": 525185,
        "segment": 176,
        "quality": 4,
        "buffer_level_before": 823,
        "buffer_level_after": 823
      },
      {
        "start_time": 525185,
        "end_time": 527465,
        "segment": 177,
        "quality": 4,
        "buffer_level_before": 1543,
        "buffer_level_after": 1543
      },
      {
        "start_time": 554400,
        "end_time": 557645,
        "segment": 162,
        "quality": 5,
        "buffer_level_before": 0,
        "buffer_level_after": 0
      },
      {
        "start_time": 557645,
        "end_time": 560709,
        "segment": 163,
        "quality": 4,
        "buffer_level_before": 0,
        "buffer_level_after": 0
      },
      {
        "start_time": 560709,
        "end_time": 562362,
        "segment": 164,
        "quality": 3,
        "buffer_level_before": 1347,
        "buffer_level_after": 1347
      },
      {
        "start_time": 562362,
        "end_time": 565078,
        "segment": 165,
        "quality": 3,
        "buffer_level_before": 1631,
        "buffer_level_after": 1631
      },
      {
        "start_time": 565078,
        "end_time": 567152,
        "segment": 166,
        "quality": 3,
        "buffer_level_before": 2557,
        "buffer_level_after": 2557
      },
      {
        "start_time": 567152,
        "end_time": 569856,
        "segment": 167,
        "quality": 4,
        "buffer_level_before": 2853,
        "buffer_level_after": 2853
      },
      {
        "start_time": 569856,
        "end_time": 572268,
        "segment": 168,
        "quality": 3,
        "buffer_level_before": 3441,
        "buffer_level_after": 3441
      },
      {
        "start_time": 572268,
        "end_time": 574810,
        "segment": 169,
        "quality": 3,
        "buffer_level_before": 3899,
        "buffer_level_after": 3899
      },
      {
        "start_time": 574810,
        "end_time": 577093,
        "segment": 170,
        "quality": 3,
        "buffer_level_before": 4616,
        "buffer_level_after": 4616
      },
      {
        "start_time": 577093,
        "end_time": 579520,
        "segment": 171,
        "quality": 3,
        "buffer_level_before": 5189,
        "buffer_level_after": 5189
      },
      {
        "start_time": 579520,
        "end_time": 583027,
        "segment": 172,
        "quality": 4,
        "buffer_level_before": 4682,
        "buffer_level_after": 4682
      },
      {
        "start_time": 583027,
        "end_time": 584730,
        "segment": 173,
        "quality": 3,
        "buffer_level_before": 5979,
        "buffer_level_after": 5979
      },
      {
        "start_time": 584730,
        "end_time": 587219,
        "segment": 174,
        "quality": 4,
        "buffer_level_before": 6490,
        "buffer_level_after": 6490
      },
      {
        "start_time": 587219,
        "end_time": 589627,
        "segment": 175,
        "quality": 4,
        "buffer_level_before": 7082,
        "buffer_level_after": 7082
      },
      {
        "start_time": 589627,
        "end_time": 592178,
        "segment": 176,
        "quality": 4,
        "buffer_level_before": 7531,
        "buffer_level_after": 7531
      },
      {
        "start_time": 592178,
        "end_time": 595980,
        "segment": 177,
        "quality": 5,
        "buffer_level_before": 6729,
        "buffer_level_after": 6729
      },
      {
        "start_time": 595980,
        "end_time": 598249,
        "segment": 178,
        "quality": 4,
        "buffer_level_before": 7460,
        "buffer_level_after": 7460
      },
      {
        "start_time": 598249,
        "end_time": 601522,
        "segment": 179,
        "quality": 5,
        "buffer_level_before": 7187,
        "buffer_level_after": 7187
      },
      {
        "start_time": 601522,
        "end_time": 604013,
        "segment": 180,
        "quality": 4,
        "buffer_level_before": 7696,
        "buffer_level_after": 7696
      },
      {
        "start_time": 604013,
        "end_time": 607623,
        "segment": 181,
        "quality": 5,
        "buffer_level_before": 7086,
        "buffer_level_after": 7086
      },
      {
        "start_time": 607623,
        "end_time": 610070,
        "segment": 182,
        "quality": 4,
        "buffer_level_before": 7639,
        "buffer_level_after": 7639
      },
      {
        "start_time": 610070,
        "end_time": 612911,
        "segment": 183,
        "quality": 5,
        "buffer_level_before": 7798,
        "buffer_level_after": 7798
      },
      {
        "start_time": 612911,
        "end_time": 614343,
        "segment": 184,
        "quality": 5,
        "buffer_level_before": 9366,
        "buffer_level_after": 9366
      },
      {
        "start_time": 614343,
        "end_time": 615621,
        "segment": 185,
        "quality": 5,
        "buffer_level_before": 11087,
        "buffer_level_after": 11087
      },
      {
        "start_time": 615621,
        "end_time": 617374,
        "segment": 186,
        "quality": 6,
        "buffer_level_before": 12335,
        "buffer_level_after": 12335
      },
      {
        "start_time": 617374,
        "end_time": 619949,
        "segment": 187,
        "quality": 7,
        "buffer_level_before": 12760,
        "buffer_level_after": 12760
      },
      {
        "start_time": 619949,
        "end_time": 622582,
        "segment": 188,
        "quality": 7,
        "buffer_level_before": 13127,
        "buffer_level_after": 13127
      },
      {
        "start_time": 622582,
        "end_time": 625837,
        "segment": 189,
        "quality": 7,
        "buffer_level_before": 12872,
        "buffer_level_after": 12872
      },
      {
        "start_time": 625837,
        "end_time": 627690,
        "segment": 190,
        "quality": 7,
        "buffer_level_before": 14019,
        "buffer_level_after": 14019
      },
      {
        "start_time": 627690,
        "end_time": 630023,
        "segment": 191,
        "quality": 7,
        "buffer_level_before": 14686,
        "buffer_level_after": 14686
      },
      {
        "start_time": 630023,
        "end_time": 634217,
        "segment": 192,
        "quality": 8,
        "buffer_level_before": 13492,
        "buffer_level_after": 13492
      },
      {
        "start_time": 634217,
        "end_time": 636442,
        "segment": 193,
        "quality": 7,
        "buffer_level_before": 14267,
        "buffer_level_after": 14267
      },
      {
        "start_time": 636442,
        "end_time": 638899,
        "segment": 194,
        "quality": 7,
        "buffer_level_before": 14810,
        "buffer_level_after": 14810
      },
      {
        "start_time": 638899,
        "end_time": 673189,
        "segment": 195,
        "quality": 8,
        "buffer_level_before": 0,
        "buffer_level_after": 0
      },
      {
        "start_time": 673189,
        "end_time": 673456,
        "segment": 196,
        "quality": 0,
        "buffer_level_before": 2733,
        "buffer_level_after": 2733
      },
      {
        "start_time": 673456,
        "end_time": 673717,
        "segment": 197,
        "quality": 0,
        "buffer_level_before": 5472,
        "buffer_level_after": 5472
      },
      {
        "start_time": 673717,
        "end_time": 673946,
        "segment": 198,
        "quality": 0,
        "buffer_level_before": 8243,
        "buffer_level_after": 8243
      }
    ],
    "prefetch_events": [],
    "seek_events": [
      {
        "seek_to_s": 365,
        "segment": 122
      },
      {
        "seek_to_s": 524,
        "segment": 175
      },
      {
        "seek_to_s": 485,
        "segment": 162
      }
    ],
    "time_series": {
      "time_points": [
        0.804,
        3.102,
        4.987,
        8.088,
        10.269,
        13.282,
        16.026,
        19.243,
        21.257,
        23.661,
        26.281,
        28.74,
        30.748,
        32.161,
        34.045,
        35.764,
        38.019,
        40.962,
        43.151,
        46.285,
        48.887,
        53.261,
        55.514,
        58.454,
        90.394,
        90.907,
        91.586,
        92.607,
        93.921,
        96.21,
        98.024,
        99.994,
        102.561,
        106.074,
        108.134,
        111.372,
        114.165,
        117.329,
        119.962,
        150.43,
        150.908,
        151.623,
        153.309,
        154.668,
        156.569,
        158.484,
        161.322,
        164.021,
        167.226,
        169.555,
        172.685,
        175.454,
        177.94,
        210.685,
        211.499,
        212.532,
        214.026,
        216.315,
        218.504,
        220.798,
        224.229,
        226.928,
        230.344,
        232.703,
        236.218,
        239.064,
        271.071,
        272.261,
        273.942,
        276.244,
        278.771,
        280.759,
        284.828,
        287.098,
        291.079,
        293.092,
        296.836,
        299.139,
        302.505,
        304.365,
        306.562,
        308.353,
        312.664,
        314.85,
        318.947,
        321.028,
        324.84,
        326.908,
        330.307,
        331.311,
        332.682,
        334.04,
        337.019,
        339.337,
        342.267,
        344.181,
        346.938,
        349.597,
        353.018,
        355.366,
        390.473,
        390.606,
        391.205,
        392.339,
        393.898,
        395.298,
        396.984,
        399.972,
        402.764,
        405.569,
        408.466,
        411.525,
        414.334,
        418.29,
        419.988,
        450.409,
        450.954,
        451.593,
        453.068,
        454.557,
        456.185,
        458.562,
        461.192,
        463.987,
        466.872,
        470.061,
        472.195,
        474.814,
        479.353,
        504.773,
        507.391,
        510.553,
        512.956,
        514.585,
        516.503,
        519.866,
        523.008,
        525.185,
        527.465,
        557.645,
        560.709,
        562.362,
        565.078,
        567.152,
        569.856,
        572.268,
        574.81,
        577.093,
        579.52,
        583.027,
        584.73,
        587.219,
        589.627,
        592.178,
        595.98,
        598.249,
        601.522,
        604.013,
        607.623,
        610.07,
        612.911,
        614.343,
        615.621,
        617.374,
        619.949,
        622.582,
        625.837,
        627.69,
        630.023,
        634.217,
        636.442,
        638.899,
        673.189,
        673.456,
        673.717,
        673.946
      ],
      "buffer_levels": [
        0.0,
        0.702,
        1.817,
        1.716,
        2.535,
        2.521,
        2.777,
        2.56,
        3.547,
        4.142,
        4.523,
        5.064,
        6.056,
        7.643,
        8.758,
        10.04,
        10.785,
        10.842,
        11.653,
        11.519,
        11.917,
        10.543,
        11.29,
        11.349,
        0.0,
        2.487,
        4.808,
        6.786,
        8.472,
        9.183,
        10.37,
        11.4,
        11.833,
        11.32,
        12.26,
        12.021,
        12.229,
        12.064,
        12.431,
        0.0,
        2.522,
        4.806,
        6.12,
        7.761,
        8.86,
        9.945,
        10.108,
        10.408,
        10.204,
        10.875,
        10.744,
        10.976,
        11.489,
        0.0,
        2.186,
        4.153,
        5.659,
        6.37,
        7.181,
        7.887,
        7.456,
        7.756,
        7.341,
        7.982,
        7.466,
        7.621,
        0.0,
        1.81,
        3.129,
        3.827,
        4.3,
        5.312,
        4.242,
        4.973,
        3.992,
        4.978,
        4.235,
        4.932,
        4.566,
        5.706,
        6.509,
        7.718,
        6.407,
        7.221,
        6.124,
        7.043,
        6.231,
        7.163,
        6.764,
        8.76,
        10.389,
        12.031,
        12.051,
        12.734,
        12.804,
        13.89,
        14.133,
        14.474,
        14.053,
        14.705,
        0.0,
        2.867,
        5.268,
        7.134,
        8.575,
        10.175,
        11.489,
        11.501,
        11.709,
        11.904,
        12.007,
        11.948,
        12.139,
        11.182,
        12.485,
        0.0,
        2.454,
        4.816,
        6.341,
        7.852,
        9.224,
        9.846,
        10.217,
        10.422,
        10.537,
        10.348,
        11.214,
        11.594,
        10.056,
        0.0,
        0.381,
        0.219,
        0.817,
        2.187,
        3.27,
        2.907,
        0.0,
        0.823,
        1.543,
        0.0,
        0.0,
        1.347,
        1.631,
        2.557,
        2.853,
        3.441,
        3.899,
        4.616,
        5.189,
        4.682,
        5.979,
        6.49,
        7.082,
        7.531,
        6.729,
        7.46,
        7.187,
        7.696,
        7.086,
        7.639,
        7.798,
        9.366,
        11.087,
        12.335,
        12.76,
        13.127,
        12.872,
        14.019,
        14.686,
        13.492,
        14.267,
        14.81,
        0.0,
        2.733,
        5.472,
        8.243
      ],
      "qualities": [
        0,
        4,
        4,
        4,
        4,
        5,
        4,
        4,
        4,
        4,
        4,
        4,
        5,
        5,
        6,
        6,
        7,
        7,
        7,
        7,
        7,
        8,
        7,
        7,
        1,
        2,
        3,
        4,
        5,
        6,
        6,
        6,
        7,
        7,
        7,
        7,
        7,
        7,
        7,
        0,
        1,
        2,
        4,
        4,
        5,
        5,
        6,
        6,
        6,
        6,
        6,
        6,
        6,
        0,
        1,
        2,
        3,
        4,
        4,
        5,
        5,
        5,
        5,
        5,
        5,
        5,
        0,
        1,
        2,
        3,
        3,
        3,
        4,
        3,
        4,
        3,
        4,
        3,
        4,
        3,
        4,
        4,
        5,
        4,
        5,
        4,
        5,
        4,
        5,
        4,
        5,
        6,
        7,
        7,
        7,
        7,
        7,
        7,
        8,
        7,
        0,
        1,
        3,
        4,
        5,
        5,
        6,
        7,
        7,
        7,
        7,
        7,
        7,
        7,
        6,
        0,
        1,
        2,
        4,
        4,
        5,
        5,
        6,
        6,
        6,
        6,
        6,
        6,
        7,
        6,
        5,
        5,
        4,
        4,
        4,
        5,
        5,
        4,
        4,
        5,
        4,
        3,
        3,
        3,
        4,
        3,
        3,
        3,
        3,
        4,
        3,
        4,
        4,
        4,
        5,
        4,
        5,
        4,
        5,
        4,
        5,
        5,
        5,
        6,
        7,
        7,
        7,
        7,
        7,
        8,
        7,
        7,
        8,
        0,
        0,
        0
      ],
      "segments": [
        0,
        1,
        2,
        3,
        4,
        5,
        6,
        7,
        8,
        9,
        10,
        11,
        12,
        13,
        14,
        15,
        16,
        17,
        18,
        19,
        20,
        21,
        22,
        23,
        24,
        25,
        26,
        27,
        28,
        29,
        30,
        31,
        32,
        33,
        34,
        35,
        36,
        37,
        38,
        39,
        40,
        41,
        42,
        43,
        44,
        45,
        46,
        47,
        48,
        49,
        50,
        51,
        52,
        53,
        54,
        55,
        56,
        57,
        58,
        59,
        60,
        61,
        62,
        63,
        64,
        65,
        66,
        67,
        68,
        69,
        70,
        71,
        72,
        73,
        74,
        75,
        76,
        77,
        78,
        79,
        80,
        81,
        82,
        83,
        84,
        85,
        86,
        87,
        88,
        89,
        90,
        91,
        92,
        93,
        94,
        95,
        96,
        97,
        98,
        99,
        100,
        101,
        102,
        103,
        104,
        105,
        106,
        107,
        108,
        109,
        110,
        111,
        112,
        113,
        114,
        115,
        116,
        117,
        118,
        119,
        120,
        121,
        122,
        123,
        124,
        125,
        126,
        127,
        128,
        122,
        123,
        124,
        125,
        126,
        127,
        128,
        175,
        176,
        177,
        162,
        163,
        164,
        165,
        166,
        167,
        168,
        169,
        170,
        171,
        172,
        173,
        174,
        175,
        176,
        177,
        178,
        179,
        180,
        181,
        182,
        183,
        184,
        185,
        186,
        187,
        188,
        189,
        190,
        191,
        192,
        193,
        194,
        195,
        196,
        197,
        198
      ]
    }
  }
}